fwdviewpy/__init__.py
fwdviewpy/main.py
fwdviewpy-0.2.7.dist-info/METADATA
fwdviewpy-0.2.7.dist-info/WHEEL
fwdviewpy-0.2.7.dist-info/top_level.txt
fwdviewpy-0.2.7.dist-info/RECORD
